OneBotAdapter/Converter.py
OneBotAdapter/Core.py
OneBotAdapter/__init__.py
erispulse_onebot11adapter-3.5.1.dist-info/licenses/LICENSE
erispulse_onebot11adapter-3.5.1.dist-info/METADATA
erispulse_onebot11adapter-3.5.1.dist-info/WHEEL
erispulse_onebot11adapter-3.5.1.dist-info/entry_points.txt
erispulse_onebot11adapter-3.5.1.dist-info/top_level.txt
erispulse_onebot11adapter-3.5.1.dist-info/RECORD
