Metadata-Version: 2.4
Name: ErisPulse-OneBot11Adapter
Version: 3.5.1
Summary: ErisPulse的OneBotV11协议适配模块，异步的OneBot触发器
Author-email: wsu2059q <wsu2059@qq.com>
License: MIT License
Project-URL: homepage, https://github.com/ErisPulse/ErisPulse-OneBot11Adapter
Requires-Python: >=3.9
License-File: LICENSE
Dynamic: license-file
